<?xml version="1.0" encoding="UTF-8"?>
<!DOCTYPE suite SYSTEM "https://testng.org/testng-1.0.dtd">
<suite name="Suite">
  <test thread-count="5" name="Test">
    <classes>
      <class name="textscripts.SuggestionSelection"/>
      <class name="textscripts.AddingAndRemovingProductFromWishlist"/>
      <class name="textscripts.CheckingManufacturerPincode"/>
      <class name="textscripts.AddingAddress"/>
      <class name="textscripts.DeleteAddress"/>
      <class name="textscripts.EnterDetailsOnProductAdding"/>
      <class name="textscripts.DateOldToNew"/>
      <class name="textscripts.CheckingPincodeTextbox"/>
      <class name="textscripts.AddProductToWishlistAndCart"/>
      <class name="textscripts.InitializingCheckout"/>
    </classes>
  </test> <!-- Test -->
</suite> <!-- Suite -->
